yubico_client/__init__.py
yubico_client/modhex.py
yubico_client/otp.py
yubico_client/py3.py
yubico_client/yubico.py
yubico_client/yubico_exceptions.py
yubico_client-1.13.0.dist-info/LICENSE
yubico_client-1.13.0.dist-info/METADATA
yubico_client-1.13.0.dist-info/NOTICE
yubico_client-1.13.0.dist-info/WHEEL
yubico_client-1.13.0.dist-info/top_level.txt
yubico_client-1.13.0.dist-info/RECORD
