Metadata-Version: 2.1
Name: yubico-client
Version: 1.13.0
Summary: Library for verifying Yubikey One Time Passwords (OTPs)
Home-page: https://github.com/Kami/python-yubico-client/
Author: Tomaz Muraus
Author-email: tomaz+pypi@tomaz.me
License: BSD
Download-URL: https://github.com/Kami/python-yubico-client/releases
Platform: UNKNOWN
Classifier: Development Status :: 4 - Beta
Classifier: Environment :: Console
Classifier: Intended Audience :: Developers
Classifier: Intended Audience :: System Administrators
Classifier: License :: OSI Approved :: BSD License
Classifier: Operating System :: OS Independent
Classifier: Programming Language :: Python
Classifier: Programming Language :: Python :: 2.7
Classifier: Programming Language :: Python :: 3.3
Classifier: Programming Language :: Python :: 3.4
Classifier: Programming Language :: Python :: 3.5
Classifier: Programming Language :: Python :: 3.6
Classifier: Programming Language :: Python :: 3.7
Classifier: Programming Language :: Python :: 3.8
Classifier: Programming Language :: Python :: Implementation :: PyPy
Classifier: Topic :: Security
Classifier: Topic :: Software Development :: Libraries :: Python Modules
Provides: yubico_client
Requires-Dist: requests (<3.0,>=2.7)
